evan_cc/__init__.py
evan_cc/cookiecutter.json
evan_cc/main.py
evan_cc/{{cookiecutter.project_slug}}/text.txt
evan_cc-0.0.7.dist-info/LICENSE
evan_cc-0.0.7.dist-info/METADATA
evan_cc-0.0.7.dist-info/WHEEL
evan_cc-0.0.7.dist-info/entry_points.txt
evan_cc-0.0.7.dist-info/top_level.txt
evan_cc-0.0.7.dist-info/RECORD
