Metadata-Version: 2.1
Name: evan-cc
Version: 0.0.7
Summary: Evan's Cookiecutter
Author-email: Evan Sizemore <evan@wool.homes>
License: MIT License
Classifier: Development Status :: 3 - Alpha
Classifier: Framework :: Django
Classifier: Intended Audience :: Developers
Classifier: License :: OSI Approved :: MIT License
Requires-Python: >=3.8
License-File: LICENSE
Requires-Dist: cookiecutter ==2.6.0
Requires-Dist: binaryornot ==0.4.4
Requires-Dist: ruff ==0.6.3
Requires-Dist: django-upgrade ==1.20.0
Requires-Dist: djlint ==1.35.2
Requires-Dist: pre-commit ==3.8.0
Requires-Dist: tox ==4.18.0
Requires-Dist: pytest ==8.3.2
Requires-Dist: pytest-xdist ==3.6.1
Requires-Dist: pytest-cookies ==0.7.0
Requires-Dist: pytest-instafail ==0.5.0
Requires-Dist: pyyaml ==6.0.2
Requires-Dist: PyGithub ==2.4.0
Requires-Dist: gitpython ==3.1.43
Requires-Dist: jinja2 ==3.1.4
Requires-Dist: requests ==2.32.3
Requires-Dist: sh ==2.0.7 ; sys_platform != "win32"
